setup.cfg
setup.py
drsync/__init__.py
drsync/drsync.py
drsync/sync.py
drsync.egg-info/PKG-INFO
drsync.egg-info/SOURCES.txt
drsync.egg-info/dependency_links.txt
drsync.egg-info/entry_points.txt
drsync.egg-info/requires.txt
drsync.egg-info/top_level.txt
drsync/data/__init__.py
drsync/data/drsync_conf.txt
drsync/data/post_reg_msg.txt
drsync/data/rsync_filter.txt