Metadata-Version: 1.1
Name: drsync
Version: 1.0.1
Summary: Syncs directories across systems
Home-page: https://github.com/sheoran/drsync
Author: Deepak sheoran
Author-email: deepak.sheoran@outlook.com
License: MIT
Keywords: development tool rsync
Platform: UNKNOWN
Classifier: Development Status :: 5 - Production/Stable
Classifier: Intended Audience :: Developers
Classifier: Topic :: Software Development :: Build Tools
Classifier: License :: OSI Approved :: MIT License
Classifier: Programming Language :: Python :: 2.7
